LICENSE
MANIFEST.in
README.md
setup.cfg
setup.py
box51/__init__.py
box51.egg-info/PKG-INFO
box51.egg-info/SOURCES.txt
box51.egg-info/dependency_links.txt
box51.egg-info/pbr.json
box51.egg-info/requires.txt
box51.egg-info/top_level.txt